sausage_links.py
sausage_links-1.0.0.dist-info/licenses/LICENSE
sausage_links-1.0.0.dist-info/METADATA
sausage_links-1.0.0.dist-info/WHEEL
sausage_links-1.0.0.dist-info/top_level.txt
sausage_links-1.0.0.dist-info/RECORD
