Metadata-Version: 2.4
Name: sausage_links
Version: 1.0.0
Summary: Implementation of the Sausage Links algorithm base Swinging Door in Python.
Author-email: "Aleksandr F. Mikhaylov (ChelAxe)" <chelaxe@gmail.com>
License-Expression: MIT
Project-URL: Documentation, https://sausagelinks.readthedocs.io/en/latest/
Project-URL: Source, https://github.com/chelaxe/SausageLinks
Project-URL: Tracker, https://github.com/chelaxe/SausageLinks/issues
Keywords: SausageLinks
Classifier: Development Status :: 5 - Production/Stable
Classifier: Operating System :: OS Independent
Classifier: Intended Audience :: Developers
Classifier: Topic :: Software Development
Classifier: Typing :: Typed
Classifier: Programming Language :: Python
Classifier: Programming Language :: Python :: 3
Classifier: Programming Language :: Python :: 3.9
Classifier: Programming Language :: Python :: 3.10
Classifier: Programming Language :: Python :: 3.11
Classifier: Programming Language :: Python :: 3.12
Classifier: Programming Language :: Python :: 3.13
Requires-Python: >=3.9
License-File: LICENSE
Dynamic: license-file
